Metadata-Version: 2.1
Name: data-generation
Version: 0.0.1
Summary: A synthetic data generation package
Home-page: https://github.com/alvaromc317/data_generation
Author: Alvaro Mendez Civieta
Author-email: almendez@est-econ.uc3m.es
License: GNU General Public License
Keywords: synthetic data
Platform: UNKNOWN
Requires-Python: >=3.5
